{
  "genres": [
    {
      "id": 1,
      "name": "эпопея"
    },
    {
      "id": 2,
      "name": "роман"
    },
    {
      "id": 3,
      "name": "повесть"
    },
    {
      "id": 4,
      "name": "рассказ"
    },
    {
      "id": 5,
      "name": "новелла"
    },
    {
      "id": 6,
      "name": "очерк"
    },
    {
      "id": 7,
      "name": "ода"
    },
    {
      "id": 8,
      "name": "лирическое стихотворение"
    },
    {
      "id": 9,
      "name": "элегия"
    },
    {
      "id": 10,
      "name": "эпиграмма"
    },
    {
      "id": 11,
      "name": "комедия"
    },
    {
      "id": 12,
      "name": "трагедия"
    }
  ],
  "books": [
    {
      "name": "Гарри Поттер и Философский камень",
      "author": "Джоан Роулинг",
      "date": "1999",
      "genre": [],
      "genreId": 3,
      "description": "Test Description...",
      "id": 1
    },
    {
      "name": "1984",
      "author": "Джордж Оруэлл",
      "date": "1920",
      "genre": [],
      "genreId": 5,
      "description": "Test Description 2",
      "id": 2
    },
    {
      "name": "Вино из одуванчиков",
      "author": "Рэй Брэдберри",
      "date": "1920",
      "genre": [],
      "genreId": 6,
      "description": "Test Description 3",
      "id": 3
    }
  ]
}